multidns.py
multidns-1.0.6.dist-info/DESCRIPTION.rst
multidns-1.0.6.dist-info/METADATA
multidns-1.0.6.dist-info/RECORD
multidns-1.0.6.dist-info/WHEEL
multidns-1.0.6.dist-info/entry_points.txt
multidns-1.0.6.dist-info/metadata.json
multidns-1.0.6.dist-info/top_level.txt
