Metadata-Version: 2.0
Name: multidns
Version: 1.0.6
Summary: relay DNS requests to multiple servers and returns the fastest answer
Home-page: UNKNOWN
Author: Mohammad Razavi
Author-email: mrazavi64@gmail.com
License: GPL
Keywords: dns iran filtering
Platform: UNKNOWN
Classifier: Topic :: Internet :: Name Service (DNS)
Classifier: Programming Language :: Python :: 2
Classifier: Programming Language :: Python :: 3
Requires-Dist: dnslib
